axon_serve/__init__.py
axon_serve/options.py
axon_serve/client/__init__.py
axon_serve/client/serve_client.py
axon_serve/convert/convert_array.py
axon_serve/convert/convert_dict.py
axon_serve/proto/service.proto
axon_serve/proto/generated/service_pb2.py
axon_serve/proto/generated/service_pb2.pyi
axon_serve/proto/generated/service_pb2_grpc.py
axon_serve/server/__init__.py
axon_serve/server/grpc_service.py
axon_serve/server/predict_service.py
axon_serve-0.0.1.dist-info/METADATA
axon_serve-0.0.1.dist-info/WHEEL
axon_serve-0.0.1.dist-info/licenses/LICENCE
axon_serve-0.0.1.dist-info/RECORD
