Metadata-Version: 2.1
Name: axon_serve
Version: 0.0.1
Summary: Simple package for ML Model serving with gRPC
Author-email: Nino Hasl <nino.hasl2@gmail.com>
License-File: LICENCE
Classifier: License :: OSI Approved :: MIT License
Classifier: Operating System :: OS Independent
Classifier: Programming Language :: Python :: 3
Requires-Python: >=3.8
Requires-Dist: grpcio-tools==1.60.0
Requires-Dist: grpcio~=1.60.0
Requires-Dist: numpy~=1.26.3
